tests/__init__.py
tests/test_utils.py
wei_office_simptool/SQLManager.py
wei_office_simptool/__init__.py
wei_office_simptool/baseColor.py
wei_office_simptool/chartsManager.py
wei_office_simptool/docManager.py
wei_office_simptool/excelManager.py
wei_office_simptool/fileManager.py
wei_office_simptool/mailManager.py
wei_office_simptool/ollamaManager.py
wei_office_simptool/stringManager.py
wei_office_simptool/textManager.py
wei_office_simptool/timingTool.py
wei_office_simptool-0.2.3.dist-info/METADATA
wei_office_simptool-0.2.3.dist-info/WHEEL
wei_office_simptool-0.2.3.dist-info/top_level.txt
wei_office_simptool-0.2.3.dist-info/RECORD
